{"web":{"client_id":"192323261443-rhiopgdtu8a27fb5o0cjs3k6v7da4nmu.apps.googleusercontent.com","project_id":"yelp-camp-haitham","auth_uri":"https://accounts.google.com/o/oauth2/auth","token_uri":"https://oauth2.googleapis.com/token","auth_provider_x509_cert_url":"https://www.googleapis.com/oauth2/v1/certs","client_secret":"Z0PlKSNA0JKVL54DaJ21PXMA","redirect_uris":["https://localhost:8000/callback","http://localhost:8000/callback"],"javascript_origins":["http://localhost:8000","http://localhost:5000","https://localhost:8000"]}}